install_ifcopenshell_python/__init__.py
install_ifcopenshell_python/__main__.py
install_ifcopenshell_python/_version.py
install_ifcopenshell_python-0.1.0.dist-info/LICENSE
install_ifcopenshell_python-0.1.0.dist-info/METADATA
install_ifcopenshell_python-0.1.0.dist-info/WHEEL
install_ifcopenshell_python-0.1.0.dist-info/top_level.txt
install_ifcopenshell_python-0.1.0.dist-info/RECORD
