Metadata-Version: 2.1
Name: install-ifcopenshell-python
Version: 0.1.0
Summary: Install ifcopenshell for python
Home-page: https://github.com/tbrus/install-ifcopenshell-python
Author: tbrus
Author-email: tomek.brus1@gmail.com
License: UNKNOWN
Project-URL: Bug Tracker, https://github.com/tbrus/install-ifcopenshell-python/issues
Platform: UNKNOWN
Classifier: Programming Language :: Python :: 3.7
Classifier: Programming Language :: Python :: 3.8
Classifier: Programming Language :: Python :: 3.9
Classifier: License :: OSI Approved :: MIT License
Classifier: Operating System :: OS Independent
Requires-Python: >=3.7
Provides-Extra: test
License-File: LICENSE
